LICENSE
README.rst
setup.py
sphinx_harumaru_themes/__init__.py
sphinx_harumaru_themes.egg-info/PKG-INFO
sphinx_harumaru_themes.egg-info/SOURCES.txt
sphinx_harumaru_themes.egg-info/dependency_links.txt
sphinx_harumaru_themes.egg-info/entry_points.txt
sphinx_harumaru_themes.egg-info/top_level.txt
sphinx_harumaru_themes/_common/domainindex.html
sphinx_harumaru_themes/_common/genindex-single.html
sphinx_harumaru_themes/_common/genindex-split.html
sphinx_harumaru_themes/_common/genindex.html
sphinx_harumaru_themes/_common/globaltoc.html
sphinx_harumaru_themes/_common/layout_dark.html
sphinx_harumaru_themes/_common/layout_light.html
sphinx_harumaru_themes/_common/localtoc.html
sphinx_harumaru_themes/_common/page.html
sphinx_harumaru_themes/_common/relations.html
sphinx_harumaru_themes/_common/search.html
sphinx_harumaru_themes/_common/sourcelink.html
sphinx_harumaru_themes/daimaru_dark_theme/layout.html
sphinx_harumaru_themes/daimaru_dark_theme/theme.conf
sphinx_harumaru_themes/daimaru_dark_theme/static/main.css
sphinx_harumaru_themes/daimaru_dark_theme/static/fonts/nunito/Nunito-Black.ttf
sphinx_harumaru_themes/daimaru_dark_theme/static/fonts/nunito/Nunito-BlackItalic.ttf
sphinx_harumaru_themes/daimaru_dark_theme/static/fonts/nunito/Nunito-Bold.ttf
sphinx_harumaru_themes/daimaru_dark_theme/static/fonts/nunito/Nunito-BoldItalic.ttf
sphinx_harumaru_themes/daimaru_dark_theme/static/fonts/nunito/Nunito-ExtraBold.ttf
sphinx_harumaru_themes/daimaru_dark_theme/static/fonts/nunito/Nunito-ExtraBoldItalic.ttf
sphinx_harumaru_themes/daimaru_dark_theme/static/fonts/nunito/Nunito-ExtraLight.ttf
sphinx_harumaru_themes/daimaru_dark_theme/static/fonts/nunito/Nunito-ExtraLightItalic.ttf
sphinx_harumaru_themes/daimaru_dark_theme/static/fonts/nunito/Nunito-HeavyItalic.ttf
sphinx_harumaru_themes/daimaru_dark_theme/static/fonts/nunito/Nunito-HeavyRegular.ttf
sphinx_harumaru_themes/daimaru_dark_theme/static/fonts/nunito/Nunito-Italic.ttf
sphinx_harumaru_themes/daimaru_dark_theme/static/fonts/nunito/Nunito-Light.ttf
sphinx_harumaru_themes/daimaru_dark_theme/static/fonts/nunito/Nunito-LightItalic.ttf
sphinx_harumaru_themes/daimaru_dark_theme/static/fonts/nunito/Nunito-Regular.ttf
