Metadata-Version: 2.1
Name: sphinx-harumaru-themes
Version: 0.8
Summary: A package with cute Sphinx documentation themes
Home-page: 
Author: DanielSDVG
Author-email: danielsdvg@gmail.com
License: MIT
Classifier: Programming Language :: Python :: 3
Classifier: License :: OSI Approved :: MIT License
Classifier: Operating System :: OS Independent
License-File: LICENSE
